discord/ext/slash/__init__.py
discord/ext/slash/abc.py
discord/ext/slash/client.py
discord/ext/slash/gateway.py
dpy_slash_ext-0.0.1a0.dist-info/METADATA
dpy_slash_ext-0.0.1a0.dist-info/WHEEL
dpy_slash_ext-0.0.1a0.dist-info/top_level.txt
dpy_slash_ext-0.0.1a0.dist-info/RECORD
