Metadata-Version: 2.1
Name: dpy-slash-ext
Version: 0.0.1a0
Summary: A discord.py slash commands extension
Home-page: UNKNOWN
Author: quiktea
Author-email: wishymovies@gmail.com
License: UNKNOWN
Project-URL: GitHub, https://github.com/quiktea/slash-ext
Keywords: python,discord.py,slash commands,discord,api,discord api
Platform: UNKNOWN
Classifier: Development Status :: 1 - Planning
Classifier: Intended Audience :: Developers
Classifier: Programming Language :: Python :: 3
Classifier: Operating System :: Unix
Classifier: Operating System :: MacOS :: MacOS X
Classifier: Operating System :: Microsoft :: Windows
Requires-Dist: discord.py
Requires-Dist: aiohttp
